turbograph/__init__.py
turbograph/py.typed
turbograph/backend/__init__.py
turbograph/backend/factory.py
turbograph/backend/igraph_backend.py
turbograph/backend/networkx_backend.py
turbograph/core/__init__.py
turbograph/core/adapter.py
turbograph/core/attribute.py
turbograph/core/constant.py
turbograph/core/exception.py
turbograph/core/funccall.py
turbograph/core/graphwrapper.py
turbograph/core/specification.py
turbograph/run/__init__.py
turbograph/run/computing.py
turbograph/run/graphbuilding.py
turbograph/run/graphchecking.py
turbograph/run/graphcomputing.py
turbograph/run/graphupdating.py
turbograph-0.6.1.dist-info/METADATA
turbograph-0.6.1.dist-info/WHEEL
turbograph-0.6.1.dist-info/licenses/LICENSE
turbograph-0.6.1.dist-info/RECORD
