Metadata-Version: 2.4
Name: turbograph
Version: 0.6.1
Summary: A Library for Quick Dependency-based Computation
Project-URL: Homepage, https://gitlab.cern.ch/particlepredatorinvasion/turbograph
Project-URL: Documentation, https://turbograph.docs.cern.ch
Project-URL: Repository, https://gitlab.cern.ch/particlepredatorinvasion/turbograph
Project-URL: Issues, https://gitlab.cern.ch/particlepredatorinvasion/turbograph/issues
Project-URL: Changelog, https://gitlab.cern.ch/particlepredatorinvasion/turbograph/-/blob/master/CHANGELOG.md
Author-email: Anthony Correia <anthony.correia@cern.ch>
License: Apache License (2.0)
License-File: LICENSE
Keywords: DAG,computation,dataflow,dependency graph,graph,python library,turbo,workflow
Classifier: Development Status :: 4 - Beta
Classifier: Intended Audience :: Science/Research
Classifier: License :: OSI Approved :: Apache Software License
Classifier: Operating System :: OS Independent
Classifier: Programming Language :: Python :: 3
Classifier: Programming Language :: Python :: 3 :: Only
Classifier: Programming Language :: Python :: 3.9
Classifier: Programming Language :: Python :: 3.10
Classifier: Programming Language :: Python :: 3.11
Classifier: Programming Language :: Python :: 3.12
Classifier: Programming Language :: Python :: 3.13
Classifier: Topic :: Scientific/Engineering
Requires-Python: >=3.9
Requires-Dist: typing-extensions; python_version < '3.11'
Provides-Extra: igraph
Requires-Dist: igraph>=0.10.0; extra == 'igraph'
Provides-Extra: networkx
Requires-Dist: networkx>=2.5; extra == 'networkx'
